pySingleCellNet/__init__.py
pySingleCellNet/_version.py
pySingleCellNet/config.py
pySingleCellNet/plotting/__init__.py
pySingleCellNet/plotting/bar.py
pySingleCellNet/plotting/dot.py
pySingleCellNet/plotting/fancy.py
pySingleCellNet/plotting/heatmap.py
pySingleCellNet/plotting/helpers.py
pySingleCellNet/plotting/scatter.py
pySingleCellNet/plotting/spatial.py
pySingleCellNet/tools/__init__.py
pySingleCellNet/tools/categorize.py
pySingleCellNet/tools/classifier.py
pySingleCellNet/tools/cluster.py
pySingleCellNet/tools/cluster_cliques.py
pySingleCellNet/tools/cluster_eval.py
pySingleCellNet/tools/comparison.py
pySingleCellNet/tools/gene.py
pySingleCellNet/tools/rank_class.py
pySingleCellNet/utils/__init__.py
pySingleCellNet/utils/adataTools.py
pySingleCellNet/utils/annotation.py
pySingleCellNet/utils/cell.py
pySingleCellNet/utils/colors.py
pySingleCellNet/utils/knn.py
pySingleCellNet/utils/misc.py
pySingleCellNet/utils/qc.py
pysinglecellnet-0.1.4.dist-info/licenses/LICENSE
pysinglecellnet-0.1.4.dist-info/METADATA
pysinglecellnet-0.1.4.dist-info/WHEEL
pysinglecellnet-0.1.4.dist-info/top_level.txt
pysinglecellnet-0.1.4.dist-info/RECORD
