Metadata-Version: 2.4
Name: pySingleCellNet
Version: 0.1.4
Summary: Single-cell classification and analysis, optimized for embryonic and fetal development
Author-email: Patrick Cahan <patrick.cahan@gmail.com>, Yuqi Tan <ytan19@jhmi.edu>
License-Expression: MIT
Project-URL: Documentation, https://cahanlab-pysinglecellnet.readthedocs-hosted.com/
Project-URL: Source, https://github.com/CahanLab/PySingleCellNet
Project-URL: Repository, https://github.com/CahanLab/PySingleCellNet.git
Project-URL: Issues, https://github.com/CahanLab/PySingleCellNet/issues
Project-URL: Changelog, https://github.com/CahanLab/PySingleCellNet/tree/master/docs/CHANGELOG.md
Keywords: single cell,cell typing,classification,embryo,embryoid,gastruloid
Requires-Python: >=3.9
License-File: LICENSE
Requires-Dist: pandas
Requires-Dist: numpy
Requires-Dist: scikit-learn
Requires-Dist: scikit-misc
Requires-Dist: scanpy
Requires-Dist: statsmodels
Requires-Dist: scipy
Requires-Dist: matplotlib
Requires-Dist: seaborn
Requires-Dist: umap-learn
Requires-Dist: mygene
Requires-Dist: palettable
Requires-Dist: gseapy
Requires-Dist: alive_progress
Requires-Dist: python-igraph
Requires-Dist: marsilea
Dynamic: license-file
